cmd/__init__.py
cmd/device_info.py
cmd/log_info.py
cmd/main.py
cmd/temple_code.py
cmd_list/__init__.py
cmd_list/device_info.py
cmd_list/log_info.py
cmd_list/main.py
cmd_list/temple_code.py
cmds/__init__.py
cmds/device_info.py
cmds/log_info.py
cmds/main.py
cmds/temple_code.py
fwk/__init__.py
fwk/adb_cmd.py
fwk/adb_status.py
fwk/api.py
fwk/apk.py
fwk/compat.py
fwk/device.py
fwk/event.py
fwk/log.py
fwk/print_oom_ad.py
fwk/pro.py
fwk/random_device.py
fwk/screen_monitor.py
fwk/utils.py
pyadb/__init__.py
pyadb/apk.py
pyadb/device.py
pyadb/main.py
pyadb/utils.py
pyadb/cmd/__init__.py
pyadb/cmd/device_info.py
pyadb/cmd/temple_code.py
padb-1.2.0.dist-info/METADATA
padb-1.2.0.dist-info/WHEEL
padb-1.2.0.dist-info/entry_points.txt
padb-1.2.0.dist-info/top_level.txt
padb-1.2.0.dist-info/RECORD
