Metadata-Version: 2.1
Name: padb
Version: 1.2.0
Summary: pyadb tools
Home-page: https://jamesfchen.github.io/pyadb/
Author: jamesfchen
Author-email: hawksjamesf@gmail.com
License: Apache2
Platform: UNKNOWN
Classifier: Development Status :: 5 - Production/Stable
Classifier: License :: OSI Approved :: Apache Software License
Classifier: Programming Language :: Python :: 3
Classifier: Programming Language :: Python :: 3.3
Classifier: Programming Language :: Python :: 3.4
Classifier: Programming Language :: Python :: 3.5
Classifier: Programming Language :: Python :: 3.6
Classifier: Programming Language :: Python :: 3.7
Classifier: Programming Language :: Python :: 3.9
Requires-Dist: cmd-fwk
